esi_remote/__init__.py
esi_remote/esi_remote.py
esi_remote/filter_list.py
esi_remote/models.py
ESIRemote-0.5.dist-info/LICENSE
ESIRemote-0.5.dist-info/METADATA
ESIRemote-0.5.dist-info/WHEEL
ESIRemote-0.5.dist-info/top_level.txt
ESIRemote-0.5.dist-info/RECORD
