Metadata-Version: 2.1
Name: ESIRemote
Version: 0.5
Summary: Python library for remote controlling the environment in FwESI
Author-email: "@dieserniko" <hello@dieserniko.link>
License: MIT License
Project-URL: Homepage, https://github.com/dieser-niko/ESIRemote
Project-URL: Repository, https://github.com/dieser-niko/ESIRemote
Project-URL: Issues, https://github.com/dieser-niko/ESIRemote/issues
Keywords: fwesi,api,wrapper
Requires-Python: >=3.9
License-File: LICENSE
Requires-Dist: requests
